colorxkat/__init__.py
colorxkat/colors.py
colorxkat/gradients.py
colorxkat/utils.py
kawaiicolors-1.0.6.dist-info/METADATA
kawaiicolors-1.0.6.dist-info/WHEEL
kawaiicolors-1.0.6.dist-info/top_level.txt
kawaiicolors-1.0.6.dist-info/RECORD
